striprtf/__init__.py
striprtf/_version.py
striprtf/striprtf.py
striprtf-0.0.27.data/scripts/striprtf
striprtf-0.0.27.dist-info/LICENSE
striprtf-0.0.27.dist-info/METADATA
striprtf-0.0.27.dist-info/WHEEL
striprtf-0.0.27.dist-info/top_level.txt
striprtf-0.0.27.dist-info/RECORD
