Metadata-Version: 2.1
Name: striprtf
Version: 0.0.27
Summary: A simple library to convert rtf to text
Home-page: https://github.com/joshy/striprtf
Author: Joshy Cyriac
Author-email: joshy@posteo.ch
License: BSD-3-Clause
Download-URL: https://github.com/joshy/striprtf/archive/v0.0.27.tar.gz
Keywords: rtf
Platform: UNKNOWN
Classifier: License :: OSI Approved :: BSD License
License-File: LICENSE
